discus/__init__.py
discus/generator.py
discus/knowledge.py
discus/schema.py
discus/datasets/__init__.py
discus/datasets/dataset.py
discus/json/__init__.py
discus/json/architecture.py
discus/json/config.py
discus/models/__init__.py
discus/models/openai.py
discus/operations/__init__.py
discus/operations/instance.py
discus/operations/instruction.py
Discus-0.1.3b0.dist-info/LICENSE
Discus-0.1.3b0.dist-info/METADATA
Discus-0.1.3b0.dist-info/WHEEL
Discus-0.1.3b0.dist-info/top_level.txt
Discus-0.1.3b0.dist-info/RECORD
