Metadata-Version: 2.1
Name: Discus
Version: 0.1.3b0
Summary: Generate high-quality data to unlock all AI possibilities
Home-page: https://github.com/discus-labs/discus.git
Author: Discus Founders
Author-email: founders@discus.ai
License: MIT
License-File: LICENSE
Requires-Dist: openai
Requires-Dist: pandas
Requires-Dist: scikit-learn
Requires-Dist: langchain ==0.0.190
Requires-Dist: chromadb ==0.3.25
Requires-Dist: tiktoken
Requires-Dist: glob2
